{"materials":[{"id":442,"path":"Resources/unity_builtin_extra\\Sprites-Default","assetBundleId":-2,"data":["Sprites-Default",5,26,3000,0,[["PixelSnap",0],["_EnableExternalAlpha",0]],[["_Color",1,1,1,1],["_RendererColor",1,1,1,1]],[["_MainTex_ST",1,1,0,0],["_Flip",1,1,1,1],["_AlphaTex_ST",1,1,0,0]],[["_MainTex",null,null],["_AlphaTex",null,null]],[]]},{"id":650,"path":"Resources/unity_builtin_extra\\Default-Material","assetBundleId":-2,"data":["Default-Material",5,66,2000,0,[["_Cutoff",0.5],["_Glossiness",0.5],["_GlossMapScale",1],["_SmoothnessTextureChannel",0],["_Metallic",0],["_SpecularHighlights",1],["_GlossyReflections",1],["_BumpScale",1],["_Parallax",0.0199999995529652],["_OcclusionStrength",1],["_DetailNormalMapScale",1],["_UVSec",0],["_Mode",0],["_SrcBlend",1],["_DstBlend",0],["_ZWrite",1]],[["_Color",1,1,1,1],["_EmissionColor",0,0,0,0.999999940395355]],[["_MainTex_ST",1,1,0,0],["_MetallicGlossMap_ST",1,1,0,0],["_BumpMap_ST",1,1,0,0],["_ParallaxMap_ST",1,1,0,0],["_OcclusionMap_ST",1,1,0,0],["_EmissionMap_ST",1,1,0,0],["_DetailMask_ST",1,1,0,0],["_DetailAlbedoMap_ST",1,1,0,0],["_DetailNormalMap_ST",1,1,0,0]],[["_MainTex",null,null],["_MetallicGlossMap",null,null],["_BumpMap",null,null],["_ParallaxMap",null,null],["_OcclusionMap",null,null],["_EmissionMap",null,null],["_DetailMask",null,null],["_DetailAlbedoMap",null,null],["_DetailNormalMap",null,null]],[["_EMISSION",1]]]},{"id":652,"path":"Resources/unity_builtin_extra\\Default-Skybox","assetBundleId":-2,"data":["Default-Skybox",5,152,1000,0,[["_SunDisk",1],["_SunSize",0.0399999991059303],["_SunSizeConvergence",5],["_AtmosphereThickness",1],["_Exposure",1.29999995231628]],[["_SkyTint",0.5,0.5,0.5,1],["_GroundColor",0.368999987840652,0.349000006914139,0.340999990701675,1]],[],[],[["_SUNDISK_SIMPLE",1]]]}],"shaders":[{"id":164,"assetBundleId":-2,"data":[[],"Legacy Shaders/Particles/Alpha Blended",null,["FOG_EXP","FOG_EXP2","FOG_LINEAR","SOFTPARTICLES_ON","STEREO_CUBEMAP_RENDER_ON","STEREO_INSTANCING_ON","STEREO_MULTIVIEW_ON","UNITY_SINGLE_PASS_STEREO","__"],[[0,0,"",0,"",0,[4,null],[0,null],[0,null],[[5,null],[10,null],[0,null]],[[5,null],[10,null],[0,null]],[14,null],[0,null],[0,null],[0,null],[255,null],[255,null],[[0,null],[0,null],[0,null],[8,null]],[[0,null],[0,null],[0,null],[8,null]],[[0,null],[0,null],[0,null],[8,null]],[["IGNOREPROJECTOR","true"],["PreviewType","Plane"],["QUEUE","Transparent"],["RenderType","Transparent"]],["FOG_EXP","FOG_EXP2","FOG_LINEAR","SOFTPARTICLES_ON","STEREO_CUBEMAP_RENDER_ON","STEREO_INSTANCING_ON","STEREO_MULTIVIEW_ON","UNITY_SINGLE_PASS_STEREO","__"],[[["__","SOFTPARTICLES_ON"],1],[["__","FOG_LINEAR","FOG_EXP","FOG_EXP2"],1]],[[0,0,[],0,1,0,0],[0,0,[],2,3,1,0]],[],0]],[],[["_TintColor",0,0.5,0.5,0.5,0.5,"",0],["_MainTex",4,0,0,0,0,"white",0],["_InvFade",3,1,0.00999999977648258,3,0,"",0]],null,null,0,0,0]},{"id":152,"assetBundleId":-2,"data":[[],"Skybox/Procedural",null,["_SUNDISK_HIGH_QUALITY","_SUNDISK_NONE","_SUNDISK_SIMPLE","STEREO_CUBEMAP_RENDER_ON","STEREO_INSTANCING_ON","STEREO_MULTIVIEW_ON","UNITY_SINGLE_PASS_STEREO"],[[0,0,"",0,"",0,[4,null],[0,null],[0,null],[[1,null],[0,null],[0,null]],[[1,null],[0,null],[0,null]],[15,null],[0,null],[0,null],[0,null],[255,null],[255,null],[[0,null],[0,null],[0,null],[8,null]],[[0,null],[0,null],[0,null],[8,null]],[[0,null],[0,null],[0,null],[8,null]],[["PreviewType","Skybox"],["QUEUE","Background"],["RenderType","Background"]],["STEREO_CUBEMAP_RENDER_ON","STEREO_INSTANCING_ON","STEREO_MULTIVIEW_ON","UNITY_SINGLE_PASS_STEREO","_SUNDISK_HIGH_QUALITY","_SUNDISK_NONE","_SUNDISK_SIMPLE"],[[["_SUNDISK_NONE","_SUNDISK_SIMPLE","_SUNDISK_HIGH_QUALITY"],0]],[[0,0,["_SUNDISK_NONE"],4,5,0,0],[0,0,["_SUNDISK_NONE"],6,7,1,0],[0,0,["_SUNDISK_SIMPLE"],8,9,0,0],[0,0,["_SUNDISK_SIMPLE"],10,11,1,0],[0,0,["_SUNDISK_HIGH_QUALITY"],12,13,0,0],[0,0,["_SUNDISK_HIGH_QUALITY"],14,15,1,0],[0,0,["_SUNDISK_NONE","_SUNDISK_SIMPLE"],4,5,0,0],[0,0,["_SUNDISK_NONE","_SUNDISK_SIMPLE"],6,7,1,0],[0,0,["_SUNDISK_HIGH_QUALITY","_SUNDISK_SIMPLE"],8,9,0,0],[0,0,["_SUNDISK_HIGH_QUALITY","_SUNDISK_SIMPLE"],10,11,1,0]],[],0]],[],[["_SunDisk",2,2,0,0,0,"",0],["_SunSize",3,0.0399999991059303,0,1,0,"",0],["_SunSizeConvergence",3,5,1,10,0,"",0],["_AtmosphereThickness",3,1,0,5,0,"",0],["_SkyTint",0,0.5,0.5,0.5,1,"",0],["_GroundColor",0,0.368999987840652,0.349000006914139,0.340999990701675,1,"",0],["_Exposure",3,1.29999995231628,0,8,0,"",0]],null,null,0,0,0]},{"id":178,"assetBundleId":-2,"data":[[],"Particles/Standard Unlit",null,["SHADOWS_DEPTH","_ALPHABLEND_ON","_ALPHAMODULATE_ON","_ALPHAPREMULTIPLY_ON","_ALPHATEST_ON","_REQUIRE_UV2","FOG_EXP","FOG_EXP2","FOG_LINEAR","_COLORADDSUBDIFF_ON","_COLORCOLOR_ON","_COLOROVERLAY_ON","_EMISSION","_FADING_ON","_NORMALMAP","INSTANCING_ON","PROCEDURAL_INSTANCING_ON","SHADOWS_CUBE","STEREO_CUBEMAP_RENDER_ON","STEREO_INSTANCING_ON","STEREO_MULTIVIEW_ON","UNITY_SINGLE_PASS_STEREO","__","_","EFFECT_BUMP","SOFTPARTICLES_ON"],[[0,0,"",0,"_GrabTexture",0,[0,null],[0,null],[0,null],[[1,null],[0,null],[0,null]],[[1,null],[0,null],[0,null]],[15,null],[0,null],[0,null],[0,null],[0,null],[0,null],[[0,null],[0,null],[0,null],[0,null]],[[0,null],[0,null],[0,null],[0,null]],[[0,null],[0,null],[0,null],[0,null]],[["LIGHTMODE","GRABPASS"]],[],[],[],[],0],[1,0,"ShadowCaster",8,"",0,[4,null],[1,null],[0,null],[[1,null],[0,null],[0,null]],[[1,null],[0,null],[0,null]],[14,null],[0,null],[0,null],[0,null],[255,null],[255,null],[[0,null],[0,null],[0,null],[8,null]],[[0,null],[0,null],[0,null],[8,null]],[[0,null],[0,null],[0,null],[8,null]],[["IGNOREPROJECTOR","true"],["LIGHTMODE","SHADOWCASTER"],["PerformanceChecks","False"],["PreviewType","Plane"],["RenderType","Opaque"],["SHADOWSUPPORT","true"]],["INSTANCING_ON","PROCEDURAL_INSTANCING_ON","SHADOWS_CUBE","SHADOWS_DEPTH","STEREO_CUBEMAP_RENDER_ON","STEREO_INSTANCING_ON","STEREO_MULTIVIEW_ON","UNITY_SINGLE_PASS_STEREO","_ALPHABLEND_ON","_ALPHAMODULATE_ON","_ALPHAPREMULTIPLY_ON","_ALPHATEST_ON","_REQUIRE_UV2","__","_"],[[["__","INSTANCING_ON","PROCEDURAL_INSTANCING_ON"],1],[["_","_ALPHATEST_ON","_ALPHABLEND_ON","_ALPHAPREMULTIPLY_ON","_ALPHAMODULATE_ON"],1],[["_","_REQUIRE_UV2"],1],[["SHADOWS_DEPTH"],0],[["SHADOWS_CUBE"],0]],[],[],0],[4,0,"",0,"",0,[4,null],[0,"_ZWrite"],[0,"_Cull"],[[0,"_SrcBlend"],[0,"_DstBlend"],[0,"_BlendOp"]],[[0,"_SrcBlend"],[0,"_DstBlend"],[0,"_BlendOp"]],[14,null],[0,null],[0,null],[0,null],[255,null],[255,null],[[0,null],[0,null],[0,null],[8,null]],[[0,null],[0,null],[0,null],[8,null]],[[0,null],[0,null],[0,null],[8,null]],[["IGNOREPROJECTOR","true"],["PerformanceChecks","False"],["PreviewType","Plane"],["RenderType","Opaque"]],["EFFECT_BUMP","FOG_EXP","FOG_EXP2","FOG_LINEAR","INSTANCING_ON","PROCEDURAL_INSTANCING_ON","SOFTPARTICLES_ON","STEREO_CUBEMAP_RENDER_ON","STEREO_INSTANCING_ON","STEREO_MULTIVIEW_ON","UNITY_SINGLE_PASS_STEREO","_ALPHABLEND_ON","_ALPHAMODULATE_ON","_ALPHAPREMULTIPLY_ON","_ALPHATEST_ON","_COLORADDSUBDIFF_ON","_COLORCOLOR_ON","_COLOROVERLAY_ON","_EMISSION","_FADING_ON","_NORMALMAP","_REQUIRE_UV2","__","_"],[[["__","SOFTPARTICLES_ON"],1],[["__","FOG_LINEAR","FOG_EXP","FOG_EXP2"],1],[["__","INSTANCING_ON","PROCEDURAL_INSTANCING_ON"],1],[["_","_NORMALMAP"],1],[["_","_FADING_ON"],1],[["_","_REQUIRE_UV2"],1],[["_","EFFECT_BUMP"],1]],[[4,0,[],16,17,0,0],[4,0,[],18,19,1,0],[4,0,["_ALPHABLEND_ON"],16,20,0,0],[4,0,["_ALPHABLEND_ON"],18,21,1,0],[4,0,["_ALPHABLEND_ON","_COLORCOLOR_ON"],16,22,0,0],[4,0,["_ALPHABLEND_ON","_COLORCOLOR_ON"],18,23,1,0]],[],0]],[],[["_MainTex",4,0,0,0,0,"white",0],["_Color",0,1,1,1,1,"",0],["_Cutoff",3,0.5,0,1,0,"",0],["_BumpScale",2,1,0,0,0,"",0],["_BumpMap",4,0,0,0,0,"bump",0],["_EmissionColor",0,0,0,0,1,"",0],["_EmissionMap",4,0,0,0,0,"white",0],["_DistortionStrength",2,1,0,0,0,"",0],["_DistortionBlend",3,0.5,0,1,0,"",0],["_SoftParticlesNearFadeDistance",2,0,0,0,0,"",0],["_SoftParticlesFarFadeDistance",2,1,0,0,0,"",0],["_CameraNearFadeDistance",2,1,0,0,0,"",0],["_CameraFarFadeDistance",2,2,0,0,0,"",0],["_Mode",2,0,0,0,0,"",1],["_ColorMode",2,0,0,0,0,"",1],["_FlipbookMode",2,0,0,0,0,"",1],["_LightingEnabled",2,0,0,0,0,"",1],["_DistortionEnabled",2,0,0,0,0,"",1],["_EmissionEnabled",2,0,0,0,0,"",1],["_BlendOp",2,0,0,0,0,"",1],["_SrcBlend",2,1,0,0,0,"",1],["_DstBlend",2,0,0,0,0,"",1],["_ZWrite",2,1,0,0,0,"",1],["_Cull",2,2,0,0,0,"",1],["_SoftParticlesEnabled",2,0,0,0,0,"",1],["_CameraFadingEnabled",2,0,0,0,0,"",1],["_SoftParticleFadeParams",1,0,0,0,0,"",1],["_CameraFadeParams",1,0,0,0,0,"",1],["_ColorAddSubDiff",1,0,0,0,0,"",1],["_DistortionStrengthScaled",2,0,0,0,0,"",1]],5,70,0,0,0]},{"id":18,"assetBundleId":-2,"data":[[],"Legacy Shaders/Diffuse",null,["DIRECTIONAL","DIRLIGHTMAP_COMBINED","FOG_EXP","FOG_EXP2","FOG_LINEAR","LIGHTMAP_ON","LIGHTPROBE_SH","SHADOWS_SCREEN","SHADOWS_SHADOWMASK","VERTEXLIGHT_ON","DIRECTIONAL_COOKIE","POINT","POINT_COOKIE","SPOT","DYNAMICLIGHTMAP_ON","INSTANCING_ON","LIGHTMAP_SHADOW_MIXING","STEREO_CUBEMAP_RENDER_ON","STEREO_INSTANCING_ON","STEREO_MULTIVIEW_ON","UNITY_SINGLE_PASS_STEREO","__"],[[0,0,"FORWARD",4,"",0,[4,null],[1,null],[2,null],[[1,null],[0,null],[0,null]],[[1,null],[0,null],[0,null]],[15,null],[0,null],[0,null],[0,null],[255,null],[255,null],[[0,null],[0,null],[0,null],[8,null]],[[0,null],[0,null],[0,null],[8,null]],[[0,null],[0,null],[0,null],[8,null]],[["LIGHTMODE","FORWARDBASE"],["RenderType","Opaque"],["SHADOWSUPPORT","true"]],["DIRECTIONAL","DIRLIGHTMAP_COMBINED","DYNAMICLIGHTMAP_ON","FOG_EXP","FOG_EXP2","FOG_LINEAR","INSTANCING_ON","LIGHTMAP_ON","LIGHTMAP_SHADOW_MIXING","LIGHTPROBE_SH","SHADOWS_SCREEN","SHADOWS_SHADOWMASK","STEREO_CUBEMAP_RENDER_ON","STEREO_INSTANCING_ON","STEREO_MULTIVIEW_ON","UNITY_SINGLE_PASS_STEREO","VERTEXLIGHT_ON","__"],[[["__","INSTANCING_ON"],1],[["__","FOG_LINEAR","FOG_EXP","FOG_EXP2"],1],[["DIRECTIONAL"],0],[["DIRECTIONAL","LIGHTPROBE_SH"],0],[["DIRECTIONAL","SHADOWS_SHADOWMASK","LIGHTPROBE_SH"],0],[["DIRECTIONAL","DYNAMICLIGHTMAP_ON"],0],[["DIRECTIONAL","LIGHTMAP_ON"],0],[["DIRECTIONAL","LIGHTMAP_ON","DYNAMICLIGHTMAP_ON"],0],[["DIRECTIONAL","LIGHTMAP_ON","LIGHTPROBE_SH"],0],[["DIRECTIONAL","LIGHTMAP_ON","LIGHTMAP_SHADOW_MIXING"],0],[["DIRECTIONAL","LIGHTMAP_ON","DYNAMICLIGHTMAP_ON","LIGHTMAP_SHADOW_MIXING"],0],[["DIRECTIONAL","LIGHTMAP_ON","LIGHTMAP_SHADOW_MIXING","LIGHTPROBE_SH"],0],[["DIRECTIONAL","DIRLIGHTMAP_COMBINED","DYNAMICLIGHTMAP_ON"],0],[["DIRECTIONAL","LIGHTMAP_ON","DIRLIGHTMAP_COMBINED"],0],[["DIRECTIONAL","LIGHTMAP_ON","DIRLIGHTMAP_COMBINED","LIGHTPROBE_SH"],0],[["DIRECTIONAL","LIGHTMAP_ON","DIRLIGHTMAP_COMBINED","DYNAMICLIGHTMAP_ON"],0],[["DIRECTIONAL","LIGHTMAP_ON","DIRLIGHTMAP_COMBINED","LIGHTMAP_SHADOW_MIXING"],0],[["DIRECTIONAL","LIGHTMAP_ON","DIRLIGHTMAP_COMBINED","LIGHTMAP_SHADOW_MIXING","LIGHTPROBE_SH"],0],[["DIRECTIONAL","LIGHTMAP_ON","DIRLIGHTMAP_COMBINED","DYNAMICLIGHTMAP_ON","LIGHTMAP_SHADOW_MIXING"],0],[["DIRECTIONAL","LIGHTMAP_ON","SHADOWS_SHADOWMASK"],0],[["DIRECTIONAL","LIGHTMAP_ON","DYNAMICLIGHTMAP_ON","SHADOWS_SHADOWMASK"],0],[["DIRECTIONAL","LIGHTMAP_ON","SHADOWS_SHADOWMASK","LIGHTPROBE_SH"],0],[["DIRECTIONAL","LIGHTMAP_ON","DIRLIGHTMAP_COMBINED","SHADOWS_SHADOWMASK"],0],[["DIRECTIONAL","LIGHTMAP_ON","DIRLIGHTMAP_COMBINED","DYNAMICLIGHTMAP_ON","SHADOWS_SHADOWMASK"],0],[["DIRECTIONAL","LIGHTMAP_ON","DIRLIGHTMAP_COMBINED","SHADOWS_SHADOWMASK","LIGHTPROBE_SH"],0],[["DIRECTIONAL","LIGHTMAP_ON","SHADOWS_SHADOWMASK","LIGHTMAP_SHADOW_MIXING"],0],[["DIRECTIONAL","LIGHTMAP_ON","DYNAMICLIGHTMAP_ON","SHADOWS_SHADOWMASK","LIGHTMAP_SHADOW_MIXING"],0],[["DIRECTIONAL","LIGHTMAP_ON","SHADOWS_SHADOWMASK","LIGHTMAP_SHADOW_MIXING","LIGHTPROBE_SH"],0],[["DIRECTIONAL","LIGHTMAP_ON","DIRLIGHTMAP_COMBINED","SHADOWS_SHADOWMASK","LIGHTMAP_SHADOW_MIXING"],0],[["DIRECTIONAL","LIGHTMAP_ON","DIRLIGHTMAP_COMBINED","DYNAMICLIGHTMAP_ON","SHADOWS_SHADOWMASK","LIGHTMAP_SHADOW_MIXING"],0],[["DIRECTIONAL","LIGHTMAP_ON","DIRLIGHTMAP_COMBINED","SHADOWS_SHADOWMASK","LIGHTMAP_SHADOW_MIXING","LIGHTPROBE_SH"],0],[["DIRECTIONAL","SHADOWS_SCREEN"],0],[["DIRECTIONAL","SHADOWS_SCREEN","LIGHTPROBE_SH"],0],[["DIRECTIONAL","DYNAMICLIGHTMAP_ON","SHADOWS_SCREEN"],0],[["DIRECTIONAL","SHADOWS_SCREEN","LIGHTMAP_SHADOW_MIXING","LIGHTPROBE_SH"],0],[["DIRECTIONAL","DYNAMICLIGHTMAP_ON","SHADOWS_SCREEN","LIGHTMAP_SHADOW_MIXING"],0],[["DIRECTIONAL","SHADOWS_SCREEN","SHADOWS_SHADOWMASK","LIGHTPROBE_SH"],0],[["DIRECTIONAL","DYNAMICLIGHTMAP_ON","SHADOWS_SCREEN","SHADOWS_SHADOWMASK"],0],[["DIRECTIONAL","SHADOWS_SCREEN","SHADOWS_SHADOWMASK","LIGHTMAP_SHADOW_MIXING","LIGHTPROBE_SH"],0],[["DIRECTIONAL","DYNAMICLIGHTMAP_ON","SHADOWS_SCREEN","SHADOWS_SHADOWMASK","LIGHTMAP_SHADOW_MIXING"],0],[["DIRECTIONAL","LIGHTMAP_ON","SHADOWS_SCREEN"],0],[["DIRECTIONAL","LIGHTMAP_ON","DYNAMICLIGHTMAP_ON","SHADOWS_SCREEN"],0],[["DIRECTIONAL","LIGHTMAP_ON","SHADOWS_SCREEN","LIGHTPROBE_SH"],0],[["DIRECTIONAL","LIGHTMAP_ON","SHADOWS_SCREEN","LIGHTMAP_SHADOW_MIXING"],0],[["DIRECTIONAL","LIGHTMAP_ON","DYNAMICLIGHTMAP_ON","SHADOWS_SCREEN","LIGHTMAP_SHADOW_MIXING"],0],[["DIRECTIONAL","LIGHTMAP_ON","SHADOWS_SCREEN","LIGHTMAP_SHADOW_MIXING","LIGHTPROBE_SH"],0],[["DIRECTIONAL","LIGHTMAP_ON","SHADOWS_SCREEN","SHADOWS_SHADOWMASK"],0],[["DIRECTIONAL","LIGHTMAP_ON","DYNAMICLIGHTMAP_ON","SHADOWS_SCREEN","SHADOWS_SHADOWMASK"],0],[["DIRECTIONAL","LIGHTMAP_ON","SHADOWS_SCREEN","SHADOWS_SHADOWMASK","LIGHTPROBE_SH"],0],[["DIRECTIONAL","LIGHTMAP_ON","SHADOWS_SCREEN","SHADOWS_SHADOWMASK","LIGHTMAP_SHADOW_MIXING"],0],[["DIRECTIONAL","LIGHTMAP_ON","DYNAMICLIGHTMAP_ON","SHADOWS_SCREEN","SHADOWS_SHADOWMASK","LIGHTMAP_SHADOW_MIXING"],0],[["DIRECTIONAL","LIGHTMAP_ON","SHADOWS_SCREEN","SHADOWS_SHADOWMASK","LIGHTMAP_SHADOW_MIXING","LIGHTPROBE_SH"],0],[["DIRECTIONAL","DIRLIGHTMAP_COMBINED","DYNAMICLIGHTMAP_ON","SHADOWS_SCREEN"],0],[["DIRECTIONAL","LIGHTMAP_ON","DIRLIGHTMAP_COMBINED","SHADOWS_SCREEN"],0],[["DIRECTIONAL","LIGHTMAP_ON","DIRLIGHTMAP_COMBINED","SHADOWS_SCREEN","LIGHTPROBE_SH"],0],[["DIRECTIONAL","LIGHTMAP_ON","DIRLIGHTMAP_COMBINED","DYNAMICLIGHTMAP_ON","SHADOWS_SCREEN"],0],[["DIRECTIONAL","LIGHTMAP_ON","DIRLIGHTMAP_COMBINED","SHADOWS_SCREEN","LIGHTMAP_SHADOW_MIXING"],0],[["DIRECTIONAL","LIGHTMAP_ON","DIRLIGHTMAP_COMBINED","SHADOWS_SCREEN","LIGHTMAP_SHADOW_MIXING","LIGHTPROBE_SH"],0],[["DIRECTIONAL","LIGHTMAP_ON","DIRLIGHTMAP_COMBINED","DYNAMICLIGHTMAP_ON","SHADOWS_SCREEN","LIGHTMAP_SHADOW_MIXING"],0],[["DIRECTIONAL","LIGHTMAP_ON","DIRLIGHTMAP_COMBINED","SHADOWS_SCREEN","SHADOWS_SHADOWMASK"],0],[["DIRECTIONAL","LIGHTMAP_ON","DIRLIGHTMAP_COMBINED","SHADOWS_SCREEN","SHADOWS_SHADOWMASK","LIGHTPROBE_SH"],0],[["DIRECTIONAL","LIGHTMAP_ON","DIRLIGHTMAP_COMBINED","DYNAMICLIGHTMAP_ON","SHADOWS_SCREEN","SHADOWS_SHADOWMASK"],0],[["DIRECTIONAL","LIGHTMAP_ON","DIRLIGHTMAP_COMBINED","SHADOWS_SCREEN","SHADOWS_SHADOWMASK","LIGHTMAP_SHADOW_MIXING"],0],[["DIRECTIONAL","LIGHTMAP_ON","DIRLIGHTMAP_COMBINED","SHADOWS_SCREEN","SHADOWS_SHADOWMASK","LIGHTMAP_SHADOW_MIXING","LIGHTPROBE_SH"],0],[["DIRECTIONAL","LIGHTMAP_ON","DIRLIGHTMAP_COMBINED","DYNAMICLIGHTMAP_ON","SHADOWS_SCREEN","SHADOWS_SHADOWMASK","LIGHTMAP_SHADOW_MIXING"],0],[["DIRECTIONAL","VERTEXLIGHT_ON"],0],[["DIRECTIONAL","VERTEXLIGHT_ON","LIGHTPROBE_SH"],0],[["DIRECTIONAL","VERTEXLIGHT_ON","DYNAMICLIGHTMAP_ON"],0],[["DIRECTIONAL","VERTEXLIGHT_ON","DIRLIGHTMAP_COMBINED","DYNAMICLIGHTMAP_ON"],0],[["DIRECTIONAL","VERTEXLIGHT_ON","SHADOWS_SCREEN"],0],[["DIRECTIONAL","VERTEXLIGHT_ON","SHADOWS_SCREEN","LIGHTPROBE_SH"],0],[["DIRECTIONAL","VERTEXLIGHT_ON","DYNAMICLIGHTMAP_ON","SHADOWS_SCREEN"],0],[["DIRECTIONAL","VERTEXLIGHT_ON","DIRLIGHTMAP_COMBINED","DYNAMICLIGHTMAP_ON","SHADOWS_SCREEN"],0],[["DIRECTIONAL","VERTEXLIGHT_ON","SHADOWS_SCREEN","LIGHTMAP_SHADOW_MIXING"],0],[["DIRECTIONAL","VERTEXLIGHT_ON","SHADOWS_SCREEN","LIGHTMAP_SHADOW_MIXING","LIGHTPROBE_SH"],0],[["DIRECTIONAL","VERTEXLIGHT_ON","DYNAMICLIGHTMAP_ON","SHADOWS_SCREEN","LIGHTMAP_SHADOW_MIXING"],0],[["DIRECTIONAL","VERTEXLIGHT_ON","DIRLIGHTMAP_COMBINED","DYNAMICLIGHTMAP_ON","SHADOWS_SCREEN","LIGHTMAP_SHADOW_MIXING"],0],[["DIRECTIONAL","VERTEXLIGHT_ON","SHADOWS_SCREEN","SHADOWS_SHADOWMASK"],0],[["DIRECTIONAL","VERTEXLIGHT_ON","SHADOWS_SCREEN","SHADOWS_SHADOWMASK","LIGHTPROBE_SH"],0],[["DIRECTIONAL","VERTEXLIGHT_ON","DYNAMICLIGHTMAP_ON","SHADOWS_SCREEN","SHADOWS_SHADOWMASK"],0],[["DIRECTIONAL","VERTEXLIGHT_ON","DIRLIGHTMAP_COMBINED","DYNAMICLIGHTMAP_ON","SHADOWS_SCREEN","SHADOWS_SHADOWMASK"],0],[["DIRECTIONAL","VERTEXLIGHT_ON","SHADOWS_SCREEN","SHADOWS_SHADOWMASK","LIGHTMAP_SHADOW_MIXING"],0],[["DIRECTIONAL","VERTEXLIGHT_ON","SHADOWS_SCREEN","SHADOWS_SHADOWMASK","LIGHTMAP_SHADOW_MIXING","LIGHTPROBE_SH"],0],[["DIRECTIONAL","VERTEXLIGHT_ON","DYNAMICLIGHTMAP_ON","SHADOWS_SCREEN","SHADOWS_SHADOWMASK","LIGHTMAP_SHADOW_MIXING"],0],[["DIRECTIONAL","VERTEXLIGHT_ON","DIRLIGHTMAP_COMBINED","DYNAMICLIGHTMAP_ON","SHADOWS_SCREEN","SHADOWS_SHADOWMASK","LIGHTMAP_SHADOW_MIXING"],0]],[[0,0,["DIRECTIONAL"],34,35,0,0],[0,0,["DIRECTIONAL"],36,37,1,0],[0,0,["DIRECTIONAL","LIGHTPROBE_SH"],38,39,0,0],[0,0,["DIRECTIONAL","LIGHTPROBE_SH"],40,41,1,0]],[],0],[1,0,"FORWARD",5,"",0,[4,null],[0,null],[2,null],[[1,null],[1,null],[0,null]],[[1,null],[1,null],[0,null]],[15,null],[0,null],[0,null],[0,null],[255,null],[255,null],[[0,null],[0,null],[0,null],[8,null]],[[0,null],[0,null],[0,null],[8,null]],[[0,null],[0,null],[0,null],[8,null]],[["LIGHTMODE","FORWARDADD"],["RenderType","Opaque"]],["DIRECTIONAL","DIRECTIONAL_COOKIE","FOG_EXP","FOG_EXP2","FOG_LINEAR","POINT","POINT_COOKIE","SPOT","STEREO_CUBEMAP_RENDER_ON","STEREO_INSTANCING_ON","STEREO_MULTIVIEW_ON","UNITY_SINGLE_PASS_STEREO","__"],[[["__","FOG_LINEAR","FOG_EXP","FOG_EXP2"],1],[["POINT"],0],[["DIRECTIONAL"],0],[["SPOT"],0],[["POINT_COOKIE"],0],[["DIRECTIONAL_COOKIE"],0]],[[1,0,["DIRECTIONAL"],42,35,0,0],[1,0,["DIRECTIONAL"],43,37,1,0]],[],0]],[],[["_Color",0,1,1,1,1,"",0],["_MainTex",4,0,0,0,0,"white",0]],5,70,0,0,0]},{"id":28,"assetBundleId":-2,"data":[[],"UI/Default",null,["UNITY_UI_ALPHACLIP","UNITY_UI_CLIP_RECT","STEREO_CUBEMAP_RENDER_ON","STEREO_INSTANCING_ON","STEREO_MULTIVIEW_ON","UNITY_SINGLE_PASS_STEREO","_"],[[0,0,"Default",0,"",0,[0,"unity_GUIZTestMode"],[0,null],[0,null],[[1,null],[10,null],[0,null]],[[1,null],[10,null],[0,null]],[0,"_ColorMask"],[0,null],[0,null],[0,"_Stencil"],[0,"_StencilReadMask"],[0,"_StencilWriteMask"],[[0,"_StencilOp"],[0,null],[0,null],[0,"_StencilComp"]],[[0,null],[0,null],[0,null],[8,null]],[[0,null],[0,null],[0,null],[8,null]],[["CanUseSpriteAtlas","true"],["IGNOREPROJECTOR","true"],["PreviewType","Plane"],["QUEUE","Transparent"],["RenderType","Transparent"]],["STEREO_CUBEMAP_RENDER_ON","STEREO_INSTANCING_ON","STEREO_MULTIVIEW_ON","UNITY_SINGLE_PASS_STEREO","UNITY_UI_ALPHACLIP","UNITY_UI_CLIP_RECT","_"],[[["_","UNITY_UI_CLIP_RECT"],1],[["_","UNITY_UI_ALPHACLIP"],1]],[[0,0,[],64,65,0,0],[0,0,[],66,67,1,0],[0,0,["UNITY_UI_ALPHACLIP"],64,68,0,0],[0,0,["UNITY_UI_ALPHACLIP"],66,69,1,0],[0,0,["UNITY_UI_CLIP_RECT"],64,70,0,0],[0,0,["UNITY_UI_CLIP_RECT"],66,71,1,0],[0,0,["UNITY_UI_ALPHACLIP","UNITY_UI_CLIP_RECT"],64,72,0,0],[0,0,["UNITY_UI_ALPHACLIP","UNITY_UI_CLIP_RECT"],66,73,1,0]],[],0]],[],[["_MainTex",4,0,0,0,0,"white",2],["_Color",0,1,1,1,1,"",0],["_StencilComp",2,8,0,0,0,"",0],["_Stencil",2,0,0,0,0,"",0],["_StencilOp",2,0,0,0,0,"",0],["_StencilWriteMask",2,255,0,0,0,"",0],["_StencilReadMask",2,255,0,0,0,"",0],["_ColorMask",2,15,0,0,0,"",0],["_UseUIAlphaClip",2,0,0,0,0,"",0]],null,null,0,0,0]},{"id":26,"assetBundleId":-2,"data":[[],"Sprites/Default",null,["PIXELSNAP_ON","ETC1_EXTERNAL_ALPHA","INSTANCING_ON","STEREO_CUBEMAP_RENDER_ON","STEREO_INSTANCING_ON","STEREO_MULTIVIEW_ON","UNITY_SINGLE_PASS_STEREO","_","__"],[[0,0,"",0,"",0,[4,null],[0,null],[0,null],[[1,null],[10,null],[0,null]],[[1,null],[10,null],[0,null]],[15,null],[0,null],[0,null],[0,null],[255,null],[255,null],[[0,null],[0,null],[0,null],[8,null]],[[0,null],[0,null],[0,null],[8,null]],[[0,null],[0,null],[0,null],[8,null]],[["CanUseSpriteAtlas","true"],["IGNOREPROJECTOR","true"],["PreviewType","Plane"],["QUEUE","Transparent"],["RenderType","Transparent"]],["ETC1_EXTERNAL_ALPHA","INSTANCING_ON","PIXELSNAP_ON","STEREO_CUBEMAP_RENDER_ON","STEREO_INSTANCING_ON","STEREO_MULTIVIEW_ON","UNITY_SINGLE_PASS_STEREO","_","__"],[[["_","ETC1_EXTERNAL_ALPHA"],1],[["__","INSTANCING_ON"],1],[["_","PIXELSNAP_ON"],1]],[[0,0,[],82,83,0,0],[0,0,[],84,85,1,0],[0,0,["PIXELSNAP_ON"],86,83,0,0],[0,0,["PIXELSNAP_ON"],87,85,1,0]],[],0]],[],[["_MainTex",4,0,0,0,0,"white",2],["_Color",0,1,1,1,1,"",0],["PixelSnap",2,0,0,0,0,"",0],["_RendererColor",0,1,1,1,1,"",1],["_Flip",1,1,1,1,1,"",1],["_AlphaTex",4,0,0,0,0,"white",2],["_EnableExternalAlpha",2,0,0,0,0,"",2]],null,null,0,0,0]},{"id":282,"assetBundleId":-2,"data":[[],"Mobile/VertexLit",null,["FOG_EXP","FOG_EXP2","FOG_LINEAR","POINT","SPOT","SHADOWS_DEPTH","STEREO_CUBEMAP_RENDER_ON","STEREO_INSTANCING_ON","STEREO_MULTIVIEW_ON","UNITY_SINGLE_PASS_STEREO","_","__","INSTANCING_ON","SHADOWS_CUBE"],[[0,0,"",1,"",0,[4,null],[1,null],[2,null],[[1,null],[0,null],[0,null]],[[1,null],[0,null],[0,null]],[15,null],[0,null],[0,null],[0,null],[255,null],[255,null],[[0,null],[0,null],[0,null],[8,null]],[[0,null],[0,null],[0,null],[8,null]],[[0,null],[0,null],[0,null],[8,null]],[["LIGHTMODE","Vertex"],["RenderType","Opaque"]],["FOG_EXP","FOG_EXP2","FOG_LINEAR","POINT","SPOT","STEREO_CUBEMAP_RENDER_ON","STEREO_INSTANCING_ON","STEREO_MULTIVIEW_ON","UNITY_SINGLE_PASS_STEREO","_"],[[["_","FOG_LINEAR","FOG_EXP","FOG_EXP2"],1],[["_","POINT","SPOT"],1]],[[0,0,[],88,89,0,0],[0,0,[],90,91,1,0]],[],0],[1,0,"",2,"",0,[4,null],[1,null],[2,null],[[1,null],[0,null],[0,null]],[[1,null],[0,null],[0,null]],[15,null],[0,null],[0,null],[0,null],[255,null],[255,null],[[0,null],[0,null],[0,null],[8,null]],[[0,null],[0,null],[0,null],[8,null]],[[0,null],[0,null],[0,null],[8,null]],[["LIGHTMODE","VertexLM"],["RenderType","Opaque"]],["FOG_EXP","FOG_EXP2","FOG_LINEAR","STEREO_CUBEMAP_RENDER_ON","STEREO_INSTANCING_ON","STEREO_MULTIVIEW_ON","UNITY_SINGLE_PASS_STEREO","__"],[[["__","FOG_LINEAR","FOG_EXP","FOG_EXP2"],1]],[[1,0,[],92,93,0,0],[1,0,[],94,95,1,0]],[],0],[2,0,"ShadowCaster",8,"",0,[4,null],[1,null],[0,null],[[1,null],[0,null],[0,null]],[[1,null],[0,null],[0,null]],[15,null],[0,null],[0,null],[0,null],[255,null],[255,null],[[0,null],[0,null],[0,null],[8,null]],[[0,null],[0,null],[0,null],[8,null]],[[0,null],[0,null],[0,null],[8,null]],[["LIGHTMODE","SHADOWCASTER"],["RenderType","Opaque"],["SHADOWSUPPORT","true"]],["INSTANCING_ON","SHADOWS_CUBE","SHADOWS_DEPTH","STEREO_CUBEMAP_RENDER_ON","STEREO_INSTANCING_ON","STEREO_MULTIVIEW_ON","UNITY_SINGLE_PASS_STEREO","__"],[[["__","INSTANCING_ON"],1],[["SHADOWS_DEPTH"],0],[["SHADOWS_CUBE"],0]],[],[],0]],[],[["_MainTex",4,0,0,0,0,"white",0]],null,null,0,0,0]},{"id":284,"assetBundleId":-2,"data":[[],"Mobile/Diffuse",null,["DIRECTIONAL","DIRLIGHTMAP_COMBINED","FOG_EXP","FOG_EXP2","FOG_LINEAR","LIGHTMAP_ON","LIGHTPROBE_SH","SHADOWS_SCREEN","SHADOWS_SHADOWMASK","VERTEXLIGHT_ON","DYNAMICLIGHTMAP_ON","INSTANCING_ON","LIGHTMAP_SHADOW_MIXING","STEREO_CUBEMAP_RENDER_ON","STEREO_INSTANCING_ON","STEREO_MULTIVIEW_ON","UNITY_SINGLE_PASS_STEREO","__"],[[0,0,"FORWARD",4,"",0,[4,null],[1,null],[2,null],[[1,null],[0,null],[0,null]],[[1,null],[0,null],[0,null]],[15,null],[0,null],[0,null],[0,null],[255,null],[255,null],[[0,null],[0,null],[0,null],[8,null]],[[0,null],[0,null],[0,null],[8,null]],[[0,null],[0,null],[0,null],[8,null]],[["LIGHTMODE","FORWARDBASE"],["RenderType","Opaque"],["SHADOWSUPPORT","true"]],["DIRECTIONAL","DIRLIGHTMAP_COMBINED","DYNAMICLIGHTMAP_ON","FOG_EXP","FOG_EXP2","FOG_LINEAR","INSTANCING_ON","LIGHTMAP_ON","LIGHTMAP_SHADOW_MIXING","LIGHTPROBE_SH","SHADOWS_SCREEN","SHADOWS_SHADOWMASK","STEREO_CUBEMAP_RENDER_ON","STEREO_INSTANCING_ON","STEREO_MULTIVIEW_ON","UNITY_SINGLE_PASS_STEREO","VERTEXLIGHT_ON","__"],[[["__","INSTANCING_ON"],1],[["__","FOG_LINEAR","FOG_EXP","FOG_EXP2"],1],[["DIRECTIONAL"],0],[["DIRECTIONAL","LIGHTPROBE_SH"],0],[["DIRECTIONAL","SHADOWS_SHADOWMASK","LIGHTPROBE_SH"],0],[["DIRECTIONAL","DYNAMICLIGHTMAP_ON"],0],[["DIRECTIONAL","LIGHTMAP_ON"],0],[["DIRECTIONAL","LIGHTMAP_ON","DYNAMICLIGHTMAP_ON"],0],[["DIRECTIONAL","LIGHTMAP_ON","LIGHTPROBE_SH"],0],[["DIRECTIONAL","LIGHTMAP_ON","LIGHTMAP_SHADOW_MIXING"],0],[["DIRECTIONAL","LIGHTMAP_ON","DYNAMICLIGHTMAP_ON","LIGHTMAP_SHADOW_MIXING"],0],[["DIRECTIONAL","LIGHTMAP_ON","LIGHTMAP_SHADOW_MIXING","LIGHTPROBE_SH"],0],[["DIRECTIONAL","DIRLIGHTMAP_COMBINED","DYNAMICLIGHTMAP_ON"],0],[["DIRECTIONAL","LIGHTMAP_ON","DIRLIGHTMAP_COMBINED"],0],[["DIRECTIONAL","LIGHTMAP_ON","DIRLIGHTMAP_COMBINED","LIGHTPROBE_SH"],0],[["DIRECTIONAL","LIGHTMAP_ON","DIRLIGHTMAP_COMBINED","DYNAMICLIGHTMAP_ON"],0],[["DIRECTIONAL","LIGHTMAP_ON","DIRLIGHTMAP_COMBINED","LIGHTMAP_SHADOW_MIXING"],0],[["DIRECTIONAL","LIGHTMAP_ON","DIRLIGHTMAP_COMBINED","LIGHTMAP_SHADOW_MIXING","LIGHTPROBE_SH"],0],[["DIRECTIONAL","LIGHTMAP_ON","DIRLIGHTMAP_COMBINED","DYNAMICLIGHTMAP_ON","LIGHTMAP_SHADOW_MIXING"],0],[["DIRECTIONAL","LIGHTMAP_ON","SHADOWS_SHADOWMASK"],0],[["DIRECTIONAL","LIGHTMAP_ON","DYNAMICLIGHTMAP_ON","SHADOWS_SHADOWMASK"],0],[["DIRECTIONAL","LIGHTMAP_ON","SHADOWS_SHADOWMASK","LIGHTPROBE_SH"],0],[["DIRECTIONAL","LIGHTMAP_ON","DIRLIGHTMAP_COMBINED","SHADOWS_SHADOWMASK"],0],[["DIRECTIONAL","LIGHTMAP_ON","DIRLIGHTMAP_COMBINED","DYNAMICLIGHTMAP_ON","SHADOWS_SHADOWMASK"],0],[["DIRECTIONAL","LIGHTMAP_ON","DIRLIGHTMAP_COMBINED","SHADOWS_SHADOWMASK","LIGHTPROBE_SH"],0],[["DIRECTIONAL","LIGHTMAP_ON","SHADOWS_SHADOWMASK","LIGHTMAP_SHADOW_MIXING"],0],[["DIRECTIONAL","LIGHTMAP_ON","DYNAMICLIGHTMAP_ON","SHADOWS_SHADOWMASK","LIGHTMAP_SHADOW_MIXING"],0],[["DIRECTIONAL","LIGHTMAP_ON","SHADOWS_SHADOWMASK","LIGHTMAP_SHADOW_MIXING","LIGHTPROBE_SH"],0],[["DIRECTIONAL","LIGHTMAP_ON","DIRLIGHTMAP_COMBINED","SHADOWS_SHADOWMASK","LIGHTMAP_SHADOW_MIXING"],0],[["DIRECTIONAL","LIGHTMAP_ON","DIRLIGHTMAP_COMBINED","DYNAMICLIGHTMAP_ON","SHADOWS_SHADOWMASK","LIGHTMAP_SHADOW_MIXING"],0],[["DIRECTIONAL","LIGHTMAP_ON","DIRLIGHTMAP_COMBINED","SHADOWS_SHADOWMASK","LIGHTMAP_SHADOW_MIXING","LIGHTPROBE_SH"],0],[["DIRECTIONAL","SHADOWS_SCREEN"],0],[["DIRECTIONAL","SHADOWS_SCREEN","LIGHTPROBE_SH"],0],[["DIRECTIONAL","DYNAMICLIGHTMAP_ON","SHADOWS_SCREEN"],0],[["DIRECTIONAL","SHADOWS_SCREEN","LIGHTMAP_SHADOW_MIXING","LIGHTPROBE_SH"],0],[["DIRECTIONAL","DYNAMICLIGHTMAP_ON","SHADOWS_SCREEN","LIGHTMAP_SHADOW_MIXING"],0],[["DIRECTIONAL","SHADOWS_SCREEN","SHADOWS_SHADOWMASK","LIGHTPROBE_SH"],0],[["DIRECTIONAL","DYNAMICLIGHTMAP_ON","SHADOWS_SCREEN","SHADOWS_SHADOWMASK"],0],[["DIRECTIONAL","SHADOWS_SCREEN","SHADOWS_SHADOWMASK","LIGHTMAP_SHADOW_MIXING","LIGHTPROBE_SH"],0],[["DIRECTIONAL","DYNAMICLIGHTMAP_ON","SHADOWS_SCREEN","SHADOWS_SHADOWMASK","LIGHTMAP_SHADOW_MIXING"],0],[["DIRECTIONAL","LIGHTMAP_ON","SHADOWS_SCREEN"],0],[["DIRECTIONAL","LIGHTMAP_ON","DYNAMICLIGHTMAP_ON","SHADOWS_SCREEN"],0],[["DIRECTIONAL","LIGHTMAP_ON","SHADOWS_SCREEN","LIGHTPROBE_SH"],0],[["DIRECTIONAL","LIGHTMAP_ON","SHADOWS_SCREEN","LIGHTMAP_SHADOW_MIXING"],0],[["DIRECTIONAL","LIGHTMAP_ON","DYNAMICLIGHTMAP_ON","SHADOWS_SCREEN","LIGHTMAP_SHADOW_MIXING"],0],[["DIRECTIONAL","LIGHTMAP_ON","SHADOWS_SCREEN","LIGHTMAP_SHADOW_MIXING","LIGHTPROBE_SH"],0],[["DIRECTIONAL","LIGHTMAP_ON","SHADOWS_SCREEN","SHADOWS_SHADOWMASK"],0],[["DIRECTIONAL","LIGHTMAP_ON","DYNAMICLIGHTMAP_ON","SHADOWS_SCREEN","SHADOWS_SHADOWMASK"],0],[["DIRECTIONAL","LIGHTMAP_ON","SHADOWS_SCREEN","SHADOWS_SHADOWMASK","LIGHTPROBE_SH"],0],[["DIRECTIONAL","LIGHTMAP_ON","SHADOWS_SCREEN","SHADOWS_SHADOWMASK","LIGHTMAP_SHADOW_MIXING"],0],[["DIRECTIONAL","LIGHTMAP_ON","DYNAMICLIGHTMAP_ON","SHADOWS_SCREEN","SHADOWS_SHADOWMASK","LIGHTMAP_SHADOW_MIXING"],0],[["DIRECTIONAL","LIGHTMAP_ON","SHADOWS_SCREEN","SHADOWS_SHADOWMASK","LIGHTMAP_SHADOW_MIXING","LIGHTPROBE_SH"],0],[["DIRECTIONAL","DIRLIGHTMAP_COMBINED","DYNAMICLIGHTMAP_ON","SHADOWS_SCREEN"],0],[["DIRECTIONAL","LIGHTMAP_ON","DIRLIGHTMAP_COMBINED","SHADOWS_SCREEN"],0],[["DIRECTIONAL","LIGHTMAP_ON","DIRLIGHTMAP_COMBINED","SHADOWS_SCREEN","LIGHTPROBE_SH"],0],[["DIRECTIONAL","LIGHTMAP_ON","DIRLIGHTMAP_COMBINED","DYNAMICLIGHTMAP_ON","SHADOWS_SCREEN"],0],[["DIRECTIONAL","LIGHTMAP_ON","DIRLIGHTMAP_COMBINED","SHADOWS_SCREEN","LIGHTMAP_SHADOW_MIXING"],0],[["DIRECTIONAL","LIGHTMAP_ON","DIRLIGHTMAP_COMBINED","SHADOWS_SCREEN","LIGHTMAP_SHADOW_MIXING","LIGHTPROBE_SH"],0],[["DIRECTIONAL","LIGHTMAP_ON","DIRLIGHTMAP_COMBINED","DYNAMICLIGHTMAP_ON","SHADOWS_SCREEN","LIGHTMAP_SHADOW_MIXING"],0],[["DIRECTIONAL","LIGHTMAP_ON","DIRLIGHTMAP_COMBINED","SHADOWS_SCREEN","SHADOWS_SHADOWMASK"],0],[["DIRECTIONAL","LIGHTMAP_ON","DIRLIGHTMAP_COMBINED","SHADOWS_SCREEN","SHADOWS_SHADOWMASK","LIGHTPROBE_SH"],0],[["DIRECTIONAL","LIGHTMAP_ON","DIRLIGHTMAP_COMBINED","DYNAMICLIGHTMAP_ON","SHADOWS_SCREEN","SHADOWS_SHADOWMASK"],0],[["DIRECTIONAL","LIGHTMAP_ON","DIRLIGHTMAP_COMBINED","SHADOWS_SCREEN","SHADOWS_SHADOWMASK","LIGHTMAP_SHADOW_MIXING"],0],[["DIRECTIONAL","LIGHTMAP_ON","DIRLIGHTMAP_COMBINED","SHADOWS_SCREEN","SHADOWS_SHADOWMASK","LIGHTMAP_SHADOW_MIXING","LIGHTPROBE_SH"],0],[["DIRECTIONAL","LIGHTMAP_ON","DIRLIGHTMAP_COMBINED","DYNAMICLIGHTMAP_ON","SHADOWS_SCREEN","SHADOWS_SHADOWMASK","LIGHTMAP_SHADOW_MIXING"],0],[["DIRECTIONAL","VERTEXLIGHT_ON"],0],[["DIRECTIONAL","VERTEXLIGHT_ON","LIGHTPROBE_SH"],0],[["DIRECTIONAL","VERTEXLIGHT_ON","DYNAMICLIGHTMAP_ON"],0],[["DIRECTIONAL","VERTEXLIGHT_ON","DIRLIGHTMAP_COMBINED","DYNAMICLIGHTMAP_ON"],0],[["DIRECTIONAL","VERTEXLIGHT_ON","SHADOWS_SCREEN"],0],[["DIRECTIONAL","VERTEXLIGHT_ON","SHADOWS_SCREEN","LIGHTPROBE_SH"],0],[["DIRECTIONAL","VERTEXLIGHT_ON","DYNAMICLIGHTMAP_ON","SHADOWS_SCREEN"],0],[["DIRECTIONAL","VERTEXLIGHT_ON","DIRLIGHTMAP_COMBINED","DYNAMICLIGHTMAP_ON","SHADOWS_SCREEN"],0],[["DIRECTIONAL","VERTEXLIGHT_ON","SHADOWS_SCREEN","LIGHTMAP_SHADOW_MIXING"],0],[["DIRECTIONAL","VERTEXLIGHT_ON","SHADOWS_SCREEN","LIGHTMAP_SHADOW_MIXING","LIGHTPROBE_SH"],0],[["DIRECTIONAL","VERTEXLIGHT_ON","DYNAMICLIGHTMAP_ON","SHADOWS_SCREEN","LIGHTMAP_SHADOW_MIXING"],0],[["DIRECTIONAL","VERTEXLIGHT_ON","DIRLIGHTMAP_COMBINED","DYNAMICLIGHTMAP_ON","SHADOWS_SCREEN","LIGHTMAP_SHADOW_MIXING"],0],[["DIRECTIONAL","VERTEXLIGHT_ON","SHADOWS_SCREEN","SHADOWS_SHADOWMASK"],0],[["DIRECTIONAL","VERTEXLIGHT_ON","SHADOWS_SCREEN","SHADOWS_SHADOWMASK","LIGHTPROBE_SH"],0],[["DIRECTIONAL","VERTEXLIGHT_ON","DYNAMICLIGHTMAP_ON","SHADOWS_SCREEN","SHADOWS_SHADOWMASK"],0],[["DIRECTIONAL","VERTEXLIGHT_ON","DIRLIGHTMAP_COMBINED","DYNAMICLIGHTMAP_ON","SHADOWS_SCREEN","SHADOWS_SHADOWMASK"],0],[["DIRECTIONAL","VERTEXLIGHT_ON","SHADOWS_SCREEN","SHADOWS_SHADOWMASK","LIGHTMAP_SHADOW_MIXING"],0],[["DIRECTIONAL","VERTEXLIGHT_ON","SHADOWS_SCREEN","SHADOWS_SHADOWMASK","LIGHTMAP_SHADOW_MIXING","LIGHTPROBE_SH"],0],[["DIRECTIONAL","VERTEXLIGHT_ON","DYNAMICLIGHTMAP_ON","SHADOWS_SCREEN","SHADOWS_SHADOWMASK","LIGHTMAP_SHADOW_MIXING"],0],[["DIRECTIONAL","VERTEXLIGHT_ON","DIRLIGHTMAP_COMBINED","DYNAMICLIGHTMAP_ON","SHADOWS_SCREEN","SHADOWS_SHADOWMASK","LIGHTMAP_SHADOW_MIXING"],0]],[[0,0,["DIRECTIONAL"],34,96,0,0],[0,0,["DIRECTIONAL"],36,97,1,0],[0,0,["DIRECTIONAL","LIGHTPROBE_SH"],38,98,0,0],[0,0,["DIRECTIONAL","LIGHTPROBE_SH"],40,99,1,0]],[],0]],[],[["_MainTex",4,0,0,0,0,"white",0]],5,282,0,0,0]},{"id":46,"assetBundleId":-2,"data":[[],"Hidden/BlitCopy",null,["STEREO_CUBEMAP_RENDER_ON","STEREO_INSTANCING_ON","STEREO_MULTIVIEW_ON","UNITY_SINGLE_PASS_STEREO"],[[0,0,"",0,"",0,[8,null],[0,null],[0,null],[[1,null],[0,null],[0,null]],[[1,null],[0,null],[0,null]],[15,null],[0,null],[0,null],[0,null],[255,null],[255,null],[[0,null],[0,null],[0,null],[8,null]],[[0,null],[0,null],[0,null],[8,null]],[[0,null],[0,null],[0,null],[8,null]],[],["STEREO_CUBEMAP_RENDER_ON","STEREO_INSTANCING_ON","STEREO_MULTIVIEW_ON","UNITY_SINGLE_PASS_STEREO"],[],[[0,0,[],100,101,0,0],[0,0,[],102,103,1,0]],[],0]],[],[["_MainTex",4,0,0,0,0,"",0],["_Color",0,1,1,1,1,"",0]],null,null,0,0,0]},{"id":70,"assetBundleId":-2,"data":[[],"Legacy Shaders/VertexLit",null,["FOG_EXP","FOG_EXP2","FOG_LINEAR","POINT","SPOT","SHADOWS_DEPTH","STEREO_CUBEMAP_RENDER_ON","STEREO_INSTANCING_ON","STEREO_MULTIVIEW_ON","UNITY_SINGLE_PASS_STEREO","_","__","INSTANCING_ON","SHADOWS_CUBE"],[[0,0,"",1,"",0,[4,null],[1,null],[2,null],[[1,null],[0,null],[0,null]],[[1,null],[0,null],[0,null]],[15,null],[0,null],[0,null],[0,null],[255,null],[255,null],[[0,null],[0,null],[0,null],[8,null]],[[0,null],[0,null],[0,null],[8,null]],[[0,null],[0,null],[0,null],[8,null]],[["LIGHTMODE","Vertex"],["RenderType","Opaque"]],["FOG_EXP","FOG_EXP2","FOG_LINEAR","POINT","SPOT","STEREO_CUBEMAP_RENDER_ON","STEREO_INSTANCING_ON","STEREO_MULTIVIEW_ON","UNITY_SINGLE_PASS_STEREO","_"],[[["_","FOG_LINEAR","FOG_EXP","FOG_EXP2"],1],[["_","POINT","SPOT"],1]],[[0,0,[],190,191,0,0],[0,0,[],192,193,1,0]],[],0],[1,0,"",2,"",0,[4,null],[1,null],[2,null],[[1,null],[0,null],[0,null]],[[1,null],[0,null],[0,null]],[15,null],[0,null],[0,null],[0,null],[255,null],[255,null],[[0,null],[0,null],[0,null],[8,null]],[[0,null],[0,null],[0,null],[8,null]],[[0,null],[0,null],[0,null],[8,null]],[["LIGHTMODE","VertexLM"],["RenderType","Opaque"]],["FOG_EXP","FOG_EXP2","FOG_LINEAR","STEREO_CUBEMAP_RENDER_ON","STEREO_INSTANCING_ON","STEREO_MULTIVIEW_ON","UNITY_SINGLE_PASS_STEREO","__"],[[["__","FOG_LINEAR","FOG_EXP","FOG_EXP2"],1]],[[1,0,[],194,195,0,0],[1,0,[],196,197,1,0]],[],0],[2,0,"ShadowCaster",8,"",0,[4,null],[1,null],[2,null],[[1,null],[0,null],[0,null]],[[1,null],[0,null],[0,null]],[15,null],[0,null],[0,null],[0,null],[255,null],[255,null],[[0,null],[0,null],[0,null],[8,null]],[[0,null],[0,null],[0,null],[8,null]],[[0,null],[0,null],[0,null],[8,null]],[["LIGHTMODE","SHADOWCASTER"],["RenderType","Opaque"],["SHADOWSUPPORT","true"]],["INSTANCING_ON","SHADOWS_CUBE","SHADOWS_DEPTH","STEREO_CUBEMAP_RENDER_ON","STEREO_INSTANCING_ON","STEREO_MULTIVIEW_ON","UNITY_SINGLE_PASS_STEREO","__"],[[["__","INSTANCING_ON"],1],[["SHADOWS_DEPTH"],0],[["SHADOWS_CUBE"],0]],[],[],0]],[],[["_Color",0,1,1,1,1,"",0],["_SpecColor",0,1,1,1,1,"",0],["_Emission",0,0,0,0,0,"",0],["_Shininess",3,0.699999988079071,0.00999999977648258,1,0,"",0],["_MainTex",4,0,0,0,0,"white",0]],null,null,0,0,0]},{"id":66,"assetBundleId":-2,"data":[[],"Standard",null,["DIRECTIONAL","DIRLIGHTMAP_COMBINED","FOG_EXP","FOG_EXP2","FOG_LINEAR","LIGHTMAP_ON","LIGHTPROBE_SH","SHADOWS_SCREEN","SHADOWS_SHADOWMASK","VERTEXLIGHT_ON","_ALPHABLEND_ON","_ALPHAPREMULTIPLY_ON","_ALPHATEST_ON","_EMISSION","_GLOSSYREFLECTIONS_OFF","_METALLICGLOSSMAP","_NORMALMAP","_PARALLAXMAP","_SMOOTHNESS_TEXTURE_ALBEDO_CHANNEL_A","_SPECULARHIGHLIGHTS_OFF","DIRECTIONAL_COOKIE","POINT","POINT_COOKIE","SHADOWS_DEPTH","SPOT","DYNAMICLIGHTMAP_ON","INSTANCING_ON","LIGHTMAP_SHADOW_MIXING","STEREO_CUBEMAP_RENDER_ON","STEREO_INSTANCING_ON","STEREO_MULTIVIEW_ON","UNITY_SINGLE_PASS_STEREO","_DETAIL_MULX2","__","_","SHADOWS_CUBE","SHADOWS_SOFT"],[[0,0,"FORWARD",4,"",0,[4,null],[0,"_ZWrite"],[2,null],[[0,"_SrcBlend"],[0,"_DstBlend"],[0,null]],[[0,"_SrcBlend"],[0,"_DstBlend"],[0,null]],[15,null],[0,null],[0,null],[0,null],[255,null],[255,null],[[0,null],[0,null],[0,null],[8,null]],[[0,null],[0,null],[0,null],[8,null]],[[0,null],[0,null],[0,null],[8,null]],[["LIGHTMODE","FORWARDBASE"],["PerformanceChecks","False"],["RenderType","Opaque"],["SHADOWSUPPORT","true"]],["DIRECTIONAL","DIRLIGHTMAP_COMBINED","DYNAMICLIGHTMAP_ON","FOG_EXP","FOG_EXP2","FOG_LINEAR","INSTANCING_ON","LIGHTMAP_ON","LIGHTMAP_SHADOW_MIXING","LIGHTPROBE_SH","SHADOWS_SCREEN","SHADOWS_SHADOWMASK","STEREO_CUBEMAP_RENDER_ON","STEREO_INSTANCING_ON","STEREO_MULTIVIEW_ON","UNITY_SINGLE_PASS_STEREO","VERTEXLIGHT_ON","_ALPHABLEND_ON","_ALPHAPREMULTIPLY_ON","_ALPHATEST_ON","_DETAIL_MULX2","_EMISSION","_GLOSSYREFLECTIONS_OFF","_METALLICGLOSSMAP","_NORMALMAP","_PARALLAXMAP","_SMOOTHNESS_TEXTURE_ALBEDO_CHANNEL_A","_SPECULARHIGHLIGHTS_OFF","__","_"],[[["__","FOG_LINEAR","FOG_EXP","FOG_EXP2"],1],[["__","INSTANCING_ON"],1],[["_","_NORMALMAP"],1],[["_","_ALPHATEST_ON","_ALPHABLEND_ON","_ALPHAPREMULTIPLY_ON"],1],[["_","_METALLICGLOSSMAP"],1],[["_","_PARALLAXMAP"],1],[["DIRECTIONAL"],0],[["DIRECTIONAL","LIGHTPROBE_SH"],0],[["DIRECTIONAL","SHADOWS_SHADOWMASK","LIGHTPROBE_SH"],0],[["DIRECTIONAL","DYNAMICLIGHTMAP_ON"],0],[["DIRECTIONAL","LIGHTMAP_ON"],0],[["DIRECTIONAL","LIGHTMAP_ON","DYNAMICLIGHTMAP_ON"],0],[["DIRECTIONAL","LIGHTMAP_ON","LIGHTPROBE_SH"],0],[["DIRECTIONAL","LIGHTMAP_ON","LIGHTMAP_SHADOW_MIXING"],0],[["DIRECTIONAL","LIGHTMAP_ON","DYNAMICLIGHTMAP_ON","LIGHTMAP_SHADOW_MIXING"],0],[["DIRECTIONAL","LIGHTMAP_ON","LIGHTMAP_SHADOW_MIXING","LIGHTPROBE_SH"],0],[["DIRECTIONAL","DIRLIGHTMAP_COMBINED","DYNAMICLIGHTMAP_ON"],0],[["DIRECTIONAL","LIGHTMAP_ON","DIRLIGHTMAP_COMBINED"],0],[["DIRECTIONAL","LIGHTMAP_ON","DIRLIGHTMAP_COMBINED","LIGHTPROBE_SH"],0],[["DIRECTIONAL","LIGHTMAP_ON","DIRLIGHTMAP_COMBINED","DYNAMICLIGHTMAP_ON"],0],[["DIRECTIONAL","LIGHTMAP_ON","DIRLIGHTMAP_COMBINED","LIGHTMAP_SHADOW_MIXING"],0],[["DIRECTIONAL","LIGHTMAP_ON","DIRLIGHTMAP_COMBINED","LIGHTMAP_SHADOW_MIXING","LIGHTPROBE_SH"],0],[["DIRECTIONAL","LIGHTMAP_ON","DIRLIGHTMAP_COMBINED","DYNAMICLIGHTMAP_ON","LIGHTMAP_SHADOW_MIXING"],0],[["DIRECTIONAL","LIGHTMAP_ON","SHADOWS_SHADOWMASK"],0],[["DIRECTIONAL","LIGHTMAP_ON","DYNAMICLIGHTMAP_ON","SHADOWS_SHADOWMASK"],0],[["DIRECTIONAL","LIGHTMAP_ON","SHADOWS_SHADOWMASK","LIGHTPROBE_SH"],0],[["DIRECTIONAL","LIGHTMAP_ON","DIRLIGHTMAP_COMBINED","SHADOWS_SHADOWMASK"],0],[["DIRECTIONAL","LIGHTMAP_ON","DIRLIGHTMAP_COMBINED","DYNAMICLIGHTMAP_ON","SHADOWS_SHADOWMASK"],0],[["DIRECTIONAL","LIGHTMAP_ON","DIRLIGHTMAP_COMBINED","SHADOWS_SHADOWMASK","LIGHTPROBE_SH"],0],[["DIRECTIONAL","LIGHTMAP_ON","SHADOWS_SHADOWMASK","LIGHTMAP_SHADOW_MIXING"],0],[["DIRECTIONAL","LIGHTMAP_ON","DYNAMICLIGHTMAP_ON","SHADOWS_SHADOWMASK","LIGHTMAP_SHADOW_MIXING"],0],[["DIRECTIONAL","LIGHTMAP_ON","SHADOWS_SHADOWMASK","LIGHTMAP_SHADOW_MIXING","LIGHTPROBE_SH"],0],[["DIRECTIONAL","LIGHTMAP_ON","DIRLIGHTMAP_COMBINED","SHADOWS_SHADOWMASK","LIGHTMAP_SHADOW_MIXING"],0],[["DIRECTIONAL","LIGHTMAP_ON","DIRLIGHTMAP_COMBINED","DYNAMICLIGHTMAP_ON","SHADOWS_SHADOWMASK","LIGHTMAP_SHADOW_MIXING"],0],[["DIRECTIONAL","LIGHTMAP_ON","DIRLIGHTMAP_COMBINED","SHADOWS_SHADOWMASK","LIGHTMAP_SHADOW_MIXING","LIGHTPROBE_SH"],0],[["DIRECTIONAL","SHADOWS_SCREEN"],0],[["DIRECTIONAL","SHADOWS_SCREEN","LIGHTPROBE_SH"],0],[["DIRECTIONAL","DYNAMICLIGHTMAP_ON","SHADOWS_SCREEN"],0],[["DIRECTIONAL","SHADOWS_SCREEN","LIGHTMAP_SHADOW_MIXING","LIGHTPROBE_SH"],0],[["DIRECTIONAL","DYNAMICLIGHTMAP_ON","SHADOWS_SCREEN","LIGHTMAP_SHADOW_MIXING"],0],[["DIRECTIONAL","SHADOWS_SCREEN","SHADOWS_SHADOWMASK","LIGHTPROBE_SH"],0],[["DIRECTIONAL","DYNAMICLIGHTMAP_ON","SHADOWS_SCREEN","SHADOWS_SHADOWMASK"],0],[["DIRECTIONAL","SHADOWS_SCREEN","SHADOWS_SHADOWMASK","LIGHTMAP_SHADOW_MIXING","LIGHTPROBE_SH"],0],[["DIRECTIONAL","DYNAMICLIGHTMAP_ON","SHADOWS_SCREEN","SHADOWS_SHADOWMASK","LIGHTMAP_SHADOW_MIXING"],0],[["DIRECTIONAL","LIGHTMAP_ON","SHADOWS_SCREEN"],0],[["DIRECTIONAL","LIGHTMAP_ON","DYNAMICLIGHTMAP_ON","SHADOWS_SCREEN"],0],[["DIRECTIONAL","LIGHTMAP_ON","SHADOWS_SCREEN","LIGHTPROBE_SH"],0],[["DIRECTIONAL","LIGHTMAP_ON","SHADOWS_SCREEN","LIGHTMAP_SHADOW_MIXING"],0],[["DIRECTIONAL","LIGHTMAP_ON","DYNAMICLIGHTMAP_ON","SHADOWS_SCREEN","LIGHTMAP_SHADOW_MIXING"],0],[["DIRECTIONAL","LIGHTMAP_ON","SHADOWS_SCREEN","LIGHTMAP_SHADOW_MIXING","LIGHTPROBE_SH"],0],[["DIRECTIONAL","LIGHTMAP_ON","SHADOWS_SCREEN","SHADOWS_SHADOWMASK"],0],[["DIRECTIONAL","LIGHTMAP_ON","DYNAMICLIGHTMAP_ON","SHADOWS_SCREEN","SHADOWS_SHADOWMASK"],0],[["DIRECTIONAL","LIGHTMAP_ON","SHADOWS_SCREEN","SHADOWS_SHADOWMASK","LIGHTPROBE_SH"],0],[["DIRECTIONAL","LIGHTMAP_ON","SHADOWS_SCREEN","SHADOWS_SHADOWMASK","LIGHTMAP_SHADOW_MIXING"],0],[["DIRECTIONAL","LIGHTMAP_ON","DYNAMICLIGHTMAP_ON","SHADOWS_SCREEN","SHADOWS_SHADOWMASK","LIGHTMAP_SHADOW_MIXING"],0],[["DIRECTIONAL","LIGHTMAP_ON","SHADOWS_SCREEN","SHADOWS_SHADOWMASK","LIGHTMAP_SHADOW_MIXING","LIGHTPROBE_SH"],0],[["DIRECTIONAL","DIRLIGHTMAP_COMBINED","DYNAMICLIGHTMAP_ON","SHADOWS_SCREEN"],0],[["DIRECTIONAL","LIGHTMAP_ON","DIRLIGHTMAP_COMBINED","SHADOWS_SCREEN"],0],[["DIRECTIONAL","LIGHTMAP_ON","DIRLIGHTMAP_COMBINED","SHADOWS_SCREEN","LIGHTPROBE_SH"],0],[["DIRECTIONAL","LIGHTMAP_ON","DIRLIGHTMAP_COMBINED","DYNAMICLIGHTMAP_ON","SHADOWS_SCREEN"],0],[["DIRECTIONAL","LIGHTMAP_ON","DIRLIGHTMAP_COMBINED","SHADOWS_SCREEN","LIGHTMAP_SHADOW_MIXING"],0],[["DIRECTIONAL","LIGHTMAP_ON","DIRLIGHTMAP_COMBINED","SHADOWS_SCREEN","LIGHTMAP_SHADOW_MIXING","LIGHTPROBE_SH"],0],[["DIRECTIONAL","LIGHTMAP_ON","DIRLIGHTMAP_COMBINED","DYNAMICLIGHTMAP_ON","SHADOWS_SCREEN","LIGHTMAP_SHADOW_MIXING"],0],[["DIRECTIONAL","LIGHTMAP_ON","DIRLIGHTMAP_COMBINED","SHADOWS_SCREEN","SHADOWS_SHADOWMASK"],0],[["DIRECTIONAL","LIGHTMAP_ON","DIRLIGHTMAP_COMBINED","SHADOWS_SCREEN","SHADOWS_SHADOWMASK","LIGHTPROBE_SH"],0],[["DIRECTIONAL","LIGHTMAP_ON","DIRLIGHTMAP_COMBINED","DYNAMICLIGHTMAP_ON","SHADOWS_SCREEN","SHADOWS_SHADOWMASK"],0],[["DIRECTIONAL","LIGHTMAP_ON","DIRLIGHTMAP_COMBINED","SHADOWS_SCREEN","SHADOWS_SHADOWMASK","LIGHTMAP_SHADOW_MIXING"],0],[["DIRECTIONAL","LIGHTMAP_ON","DIRLIGHTMAP_COMBINED","SHADOWS_SCREEN","SHADOWS_SHADOWMASK","LIGHTMAP_SHADOW_MIXING","LIGHTPROBE_SH"],0],[["DIRECTIONAL","LIGHTMAP_ON","DIRLIGHTMAP_COMBINED","DYNAMICLIGHTMAP_ON","SHADOWS_SCREEN","SHADOWS_SHADOWMASK","LIGHTMAP_SHADOW_MIXING"],0],[["DIRECTIONAL","VERTEXLIGHT_ON"],0],[["DIRECTIONAL","VERTEXLIGHT_ON","LIGHTPROBE_SH"],0],[["DIRECTIONAL","VERTEXLIGHT_ON","DYNAMICLIGHTMAP_ON"],0],[["DIRECTIONAL","VERTEXLIGHT_ON","DIRLIGHTMAP_COMBINED","DYNAMICLIGHTMAP_ON"],0],[["DIRECTIONAL","VERTEXLIGHT_ON","SHADOWS_SCREEN"],0],[["DIRECTIONAL","VERTEXLIGHT_ON","SHADOWS_SCREEN","LIGHTPROBE_SH"],0],[["DIRECTIONAL","VERTEXLIGHT_ON","DYNAMICLIGHTMAP_ON","SHADOWS_SCREEN"],0],[["DIRECTIONAL","VERTEXLIGHT_ON","DIRLIGHTMAP_COMBINED","DYNAMICLIGHTMAP_ON","SHADOWS_SCREEN"],0],[["DIRECTIONAL","VERTEXLIGHT_ON","SHADOWS_SCREEN","LIGHTMAP_SHADOW_MIXING"],0],[["DIRECTIONAL","VERTEXLIGHT_ON","SHADOWS_SCREEN","LIGHTMAP_SHADOW_MIXING","LIGHTPROBE_SH"],0],[["DIRECTIONAL","VERTEXLIGHT_ON","DYNAMICLIGHTMAP_ON","SHADOWS_SCREEN","LIGHTMAP_SHADOW_MIXING"],0],[["DIRECTIONAL","VERTEXLIGHT_ON","DIRLIGHTMAP_COMBINED","DYNAMICLIGHTMAP_ON","SHADOWS_SCREEN","LIGHTMAP_SHADOW_MIXING"],0],[["DIRECTIONAL","VERTEXLIGHT_ON","SHADOWS_SCREEN","SHADOWS_SHADOWMASK"],0],[["DIRECTIONAL","VERTEXLIGHT_ON","SHADOWS_SCREEN","SHADOWS_SHADOWMASK","LIGHTPROBE_SH"],0],[["DIRECTIONAL","VERTEXLIGHT_ON","DYNAMICLIGHTMAP_ON","SHADOWS_SCREEN","SHADOWS_SHADOWMASK"],0],[["DIRECTIONAL","VERTEXLIGHT_ON","DIRLIGHTMAP_COMBINED","DYNAMICLIGHTMAP_ON","SHADOWS_SCREEN","SHADOWS_SHADOWMASK"],0],[["DIRECTIONAL","VERTEXLIGHT_ON","SHADOWS_SCREEN","SHADOWS_SHADOWMASK","LIGHTMAP_SHADOW_MIXING"],0],[["DIRECTIONAL","VERTEXLIGHT_ON","SHADOWS_SCREEN","SHADOWS_SHADOWMASK","LIGHTMAP_SHADOW_MIXING","LIGHTPROBE_SH"],0],[["DIRECTIONAL","VERTEXLIGHT_ON","DYNAMICLIGHTMAP_ON","SHADOWS_SCREEN","SHADOWS_SHADOWMASK","LIGHTMAP_SHADOW_MIXING"],0],[["DIRECTIONAL","VERTEXLIGHT_ON","DIRLIGHTMAP_COMBINED","DYNAMICLIGHTMAP_ON","SHADOWS_SCREEN","SHADOWS_SHADOWMASK","LIGHTMAP_SHADOW_MIXING"],0]],[[0,0,["DIRECTIONAL"],198,199,0,0],[0,0,["DIRECTIONAL"],200,201,1,0],[0,0,["DIRECTIONAL","LIGHTPROBE_SH"],202,203,0,0],[0,0,["DIRECTIONAL","LIGHTPROBE_SH"],204,205,1,0],[0,0,["DIRECTIONAL","_EMISSION"],198,206,0,0],[0,0,["DIRECTIONAL","_EMISSION"],200,207,1,0],[0,0,["DIRECTIONAL","LIGHTPROBE_SH","_EMISSION"],202,208,0,0],[0,0,["DIRECTIONAL","LIGHTPROBE_SH","_EMISSION"],204,209,1,0]],[],0],[1,0,"FORWARD_DELTA",5,"",0,[4,null],[0,null],[2,null],[[0,"_SrcBlend"],[1,null],[0,null]],[[0,"_SrcBlend"],[1,null],[0,null]],[15,null],[0,null],[0,null],[0,null],[255,null],[255,null],[[0,null],[0,null],[0,null],[8,null]],[[0,null],[0,null],[0,null],[8,null]],[[0,null],[0,null],[0,null],[8,null]],[["LIGHTMODE","FORWARDADD"],["PerformanceChecks","False"],["RenderType","Opaque"],["SHADOWSUPPORT","true"]],["DIRECTIONAL","DIRECTIONAL_COOKIE","FOG_EXP","FOG_EXP2","FOG_LINEAR","LIGHTMAP_SHADOW_MIXING","POINT","POINT_COOKIE","SHADOWS_CUBE","SHADOWS_DEPTH","SHADOWS_SCREEN","SHADOWS_SHADOWMASK","SHADOWS_SOFT","SPOT","STEREO_CUBEMAP_RENDER_ON","STEREO_INSTANCING_ON","STEREO_MULTIVIEW_ON","UNITY_SINGLE_PASS_STEREO","_ALPHABLEND_ON","_ALPHAPREMULTIPLY_ON","_ALPHATEST_ON","_DETAIL_MULX2","_METALLICGLOSSMAP","_NORMALMAP","_PARALLAXMAP","_SMOOTHNESS_TEXTURE_ALBEDO_CHANNEL_A","_SPECULARHIGHLIGHTS_OFF","__","_"],[[["__","FOG_LINEAR","FOG_EXP","FOG_EXP2"],1],[["_","_NORMALMAP"],1],[["_","_ALPHATEST_ON","_ALPHABLEND_ON","_ALPHAPREMULTIPLY_ON"],1],[["_","_METALLICGLOSSMAP"],1],[["_","_PARALLAXMAP"],1],[["POINT"],0],[["DIRECTIONAL"],0],[["SPOT"],0],[["POINT_COOKIE"],0],[["DIRECTIONAL_COOKIE"],0],[["POINT","SHADOWS_SHADOWMASK"],0],[["DIRECTIONAL","SHADOWS_SHADOWMASK"],0],[["SPOT","SHADOWS_SHADOWMASK"],0],[["POINT_COOKIE","SHADOWS_SHADOWMASK"],0],[["DIRECTIONAL_COOKIE","SHADOWS_SHADOWMASK"],0],[["POINT","SHADOWS_SHADOWMASK","LIGHTMAP_SHADOW_MIXING"],0],[["DIRECTIONAL","SHADOWS_SHADOWMASK","LIGHTMAP_SHADOW_MIXING"],0],[["SPOT","SHADOWS_SHADOWMASK","LIGHTMAP_SHADOW_MIXING"],0],[["POINT_COOKIE","SHADOWS_SHADOWMASK","LIGHTMAP_SHADOW_MIXING"],0],[["DIRECTIONAL_COOKIE","SHADOWS_SHADOWMASK","LIGHTMAP_SHADOW_MIXING"],0],[["SPOT","SHADOWS_DEPTH"],0],[["SPOT","SHADOWS_DEPTH","SHADOWS_SOFT"],0],[["SPOT","SHADOWS_DEPTH","LIGHTMAP_SHADOW_MIXING"],0],[["SPOT","SHADOWS_DEPTH","SHADOWS_SOFT","LIGHTMAP_SHADOW_MIXING"],0],[["SPOT","SHADOWS_DEPTH","SHADOWS_SHADOWMASK"],0],[["SPOT","SHADOWS_DEPTH","SHADOWS_SOFT","SHADOWS_SHADOWMASK"],0],[["SPOT","SHADOWS_DEPTH","SHADOWS_SHADOWMASK","LIGHTMAP_SHADOW_MIXING"],0],[["SPOT","SHADOWS_DEPTH","SHADOWS_SOFT","SHADOWS_SHADOWMASK","LIGHTMAP_SHADOW_MIXING"],0],[["DIRECTIONAL","SHADOWS_SCREEN"],0],[["DIRECTIONAL_COOKIE","SHADOWS_SCREEN"],0],[["DIRECTIONAL","SHADOWS_SCREEN","LIGHTMAP_SHADOW_MIXING"],0],[["DIRECTIONAL_COOKIE","SHADOWS_SCREEN","LIGHTMAP_SHADOW_MIXING"],0],[["DIRECTIONAL","SHADOWS_SCREEN","SHADOWS_SHADOWMASK"],0],[["DIRECTIONAL_COOKIE","SHADOWS_SCREEN","SHADOWS_SHADOWMASK"],0],[["DIRECTIONAL","SHADOWS_SCREEN","SHADOWS_SHADOWMASK","LIGHTMAP_SHADOW_MIXING"],0],[["DIRECTIONAL_COOKIE","SHADOWS_SCREEN","SHADOWS_SHADOWMASK","LIGHTMAP_SHADOW_MIXING"],0],[["POINT","SHADOWS_CUBE"],0],[["POINT","SHADOWS_CUBE","SHADOWS_SOFT"],0],[["POINT","SHADOWS_CUBE","LIGHTMAP_SHADOW_MIXING"],0],[["POINT","SHADOWS_CUBE","SHADOWS_SOFT","LIGHTMAP_SHADOW_MIXING"],0],[["POINT","SHADOWS_CUBE","SHADOWS_SHADOWMASK"],0],[["POINT","SHADOWS_CUBE","SHADOWS_SOFT","SHADOWS_SHADOWMASK"],0],[["POINT","SHADOWS_CUBE","SHADOWS_SHADOWMASK","LIGHTMAP_SHADOW_MIXING"],0],[["POINT","SHADOWS_CUBE","SHADOWS_SOFT","SHADOWS_SHADOWMASK","LIGHTMAP_SHADOW_MIXING"],0],[["POINT_COOKIE","SHADOWS_CUBE"],0],[["POINT_COOKIE","SHADOWS_CUBE","SHADOWS_SOFT"],0],[["POINT_COOKIE","SHADOWS_CUBE","LIGHTMAP_SHADOW_MIXING"],0],[["POINT_COOKIE","SHADOWS_CUBE","SHADOWS_SOFT","LIGHTMAP_SHADOW_MIXING"],0],[["POINT_COOKIE","SHADOWS_CUBE","SHADOWS_SHADOWMASK"],0],[["POINT_COOKIE","SHADOWS_CUBE","SHADOWS_SOFT","SHADOWS_SHADOWMASK"],0],[["POINT_COOKIE","SHADOWS_CUBE","SHADOWS_SHADOWMASK","LIGHTMAP_SHADOW_MIXING"],0],[["POINT_COOKIE","SHADOWS_CUBE","SHADOWS_SOFT","SHADOWS_SHADOWMASK","LIGHTMAP_SHADOW_MIXING"],0]],[[1,0,["DIRECTIONAL"],210,211,0,0],[1,0,["DIRECTIONAL"],212,213,1,0]],[],0],[2,0,"ShadowCaster",8,"",0,[4,null],[1,null],[2,null],[[1,null],[0,null],[0,null]],[[1,null],[0,null],[0,null]],[15,null],[0,null],[0,null],[0,null],[255,null],[255,null],[[0,null],[0,null],[0,null],[8,null]],[[0,null],[0,null],[0,null],[8,null]],[[0,null],[0,null],[0,null],[8,null]],[["LIGHTMODE","SHADOWCASTER"],["PerformanceChecks","False"],["RenderType","Opaque"],["SHADOWSUPPORT","true"]],["INSTANCING_ON","SHADOWS_CUBE","SHADOWS_DEPTH","STEREO_CUBEMAP_RENDER_ON","STEREO_INSTANCING_ON","STEREO_MULTIVIEW_ON","UNITY_SINGLE_PASS_STEREO","_ALPHABLEND_ON","_ALPHAPREMULTIPLY_ON","_ALPHATEST_ON","_METALLICGLOSSMAP","_PARALLAXMAP","_SMOOTHNESS_TEXTURE_ALBEDO_CHANNEL_A","__","_"],[[["__","INSTANCING_ON"],1],[["_","_ALPHATEST_ON","_ALPHABLEND_ON","_ALPHAPREMULTIPLY_ON"],1],[["_","_METALLICGLOSSMAP"],1],[["_","_PARALLAXMAP"],1],[["SHADOWS_DEPTH"],0],[["SHADOWS_CUBE"],0]],[],[],0]],[],[["_Color",0,1,1,1,1,"",0],["_MainTex",4,0,0,0,0,"white",0],["_Cutoff",3,0.5,0,1,0,"",0],["_Glossiness",3,0.5,0,1,0,"",0],["_GlossMapScale",3,1,0,1,0,"",0],["_SmoothnessTextureChannel",2,0,0,0,0,"",0],["_Metallic",3,0,0,1,0,"",32],["_MetallicGlossMap",4,0,0,0,0,"white",0],["_SpecularHighlights",2,1,0,0,0,"",0],["_GlossyReflections",2,1,0,0,0,"",0],["_BumpScale",2,1,0,0,0,"",0],["_BumpMap",4,0,0,0,0,"bump",8],["_Parallax",3,0.0199999995529652,0.00499999988824129,0.0799999982118607,0,"",0],["_ParallaxMap",4,0,0,0,0,"black",0],["_OcclusionStrength",3,1,0,1,0,"",0],["_OcclusionMap",4,0,0,0,0,"white",0],["_EmissionColor",0,0,0,0,1,"",0],["_EmissionMap",4,0,0,0,0,"white",0],["_DetailMask",4,0,0,0,0,"white",0],["_DetailAlbedoMap",4,0,0,0,0,"grey",0],["_DetailNormalMapScale",2,1,0,0,0,"",0],["_DetailNormalMap",4,0,0,0,0,"bump",8],["_UVSec",2,0,0,0,0,"",0],["_Mode",2,0,0,0,0,"",1],["_SrcBlend",2,1,0,0,0,"",1],["_DstBlend",2,0,0,0,0,"",1],["_ZWrite",2,1,0,0,0,"",1]],5,70,0,0,0]}],"textures":[{"id":644,"type":0,"path":"Resources/unity_builtin_extra\\Default-Particle","assetBundleId":-2,"data":["Default-Particle",64,64,7,1,1,0,4,0,0,1,8,0,0,0,0]}],"cubemaps":[{"id":46802,"type":2,"path":"Assets/Scenes/SampleScene.unity/PrefilteredEnvironment.exr","assetBundleId":-2,"data":["",-655728,8,0,128,0,2,[0,0,0.25,0.5,0,0.5,0.25,1,0.25,0,0.5,0.5,0.25,0.5,0.5,1,0.5,0,0.75,0.5,0.75,0,1,0.5,0.5,0.5,0.625,0.75,0.5,0.75,0.625,1,0.625,0.5,0.75,0.75,0.625,0.75,0.75,1,0.75,0.5,0.875,0.75,0.875,0.5,1,0.75,0.75,0.75,0.8125,0.875,0.75,0.875,0.8125,1,0.8125,0.75,0.875,0.875,0.8125,0.875,0.875,1,0.875,0.75,0.9375,0.875,0.9375,0.75,1,0.875,0.875,0.875,0.90625,0.9375,0.875,0.9375,0.90625,1,0.90625,0.875,0.9375,0.9375,0.90625,0.9375,0.9375,1,0.9375,0.875,0.96875,0.9375,0.96875,0.875,1,0.9375,0.9375,0.9375,0.953125,0.96875,0.9375,0.96875,0.953125,1,0.953125,0.9375,0.96875,0.96875,0.953125,0.96875,0.96875,1,0.96875,0.9375,0.984375,0.96875,0.984375,0.9375,1,0.96875,0.96875,0.96875,0.9765625,0.984375,0.96875,0.984375,0.9765625,1,0.9765625,0.96875,0.984375,0.984375,0.9765625,0.984375,0.984375,1,0.984375,0.96875,0.9921875,0.984375,0.9921875,0.96875,1,0.984375,0.984375,0.984375,0.98828125,0.9921875,0.984375,0.9921875,0.98828125,1,0.98828125,0.984375,0.9921875,0.9921875,0.98828125,0.9921875,0.9921875,1,0.9921875,0.984375,0.99609375,0.9921875,0.99609375,0.984375,1,0.9921875,0.9921875,0.9921875,0.994140625,0.99609375,0.9921875,0.99609375,0.994140625,1,0.994140625,0.9921875,0.99609375,0.99609375,0.994140625,0.99609375,0.99609375,1,0.99609375,0.9921875,0.998046875,0.99609375,0.998046875,0.9921875,1,0.99609375],1,1]}],"resources":[{"id":0,"assetBundleId":-2,"data":[[["unity_builtin_extra",5,66],["unity_builtin_extra",4,650],["unity_builtin_extra",5,26],["unity_builtin_extra",4,442],["unity_builtin_extra",5,284],["unity_builtin_extra",5,164],["unity_builtin_extra",14,644],["unity_builtin_extra",5,178],["unity_builtin_extra",5,152],["unity_builtin_extra",4,652],["unity_builtin_extra",5,28],["dotweensettings",42,23470],["fonts & materials/liberationsans sdf",14,24968],["fonts & materials/liberationsans sdf",4,25016],["fonts & materials/liberationsans sdf - fallback",14,24998],["fonts & materials/liberationsans sdf - fallback",4,24994],["fonts & materials/liberationsans sdf - fallback",20,24996],["fonts & materials/liberationsans sdf",20,25010],["sprite assets/emojione",4,24978],["sprite assets/emojione",44,24980],["style sheets/default style sheet",45,24990],["linebreaking leading characters",46,25012],["linebreaking following characters",46,25014],["tmp settings",43,25008]],[23798,23802,24634,23802,23800,23802,23806,23810,24640,23810,23808,23810,24506,24534,24538,24534,24500,23790,24602,24534,24512,23790,23792,23790,24580,24534,24498,24494,24574,24494,24578,24494,24514,24550,24556,24550,24560,24550,24530,24550,24504,23790,24628,24550,24624,24550,24630,24550,24626,24550,24604,24550,24600,24550,24520,23790,24522,23790,24524,23790,24586,24550,24584,24550,24552,23790,24502,23790,-655420,-655414,24566,23790,-655426,-655414,-655416,-655414,24536,23790,24542,23790,24544,23790,23816,23790,-655444,-655414,24590,23790,24592,23790,24596,23790,24598,23790,24570,23790,24572,23790,-655452,-655414,-655460,-655414,-655468,-655414,24554,23790,-655446,-655414,24546,23790,24548,23790,-655432,-655414,-655166,-655160,-655172,-655160,-655162,-655160,-655190,-655160,-655198,-655160,-655206,-655160,-655214,-655160,-655192,-655160,-655178,-655160,-655300,-655294,-655306,-655294,-655296,-655294,-655324,-655294,-655332,-655294,-655340,-655294,-655348,-655294,-655326,-655294,-655312,-655294,24080,24188,24008,24188,23992,24188,24052,24188,23964,24188,24060,24188,23952,24188,23944,24188,24032,24188,24056,24188,24004,24188,23956,24188,23972,24188,24020,24188,23948,24188,23936,24188,24048,24188,23976,24188,24088,24188,23960,24188,24036,24188,23968,24188,23996,24188,24028,24188,24072,24188,24024,24188,24000,24188,23926,24188,24016,24188,23980,24188,24068,24188,24040,24188,24012,24188,24064,24188,24044,24188,23984,24188,24084,24188,23932,24188,23988,24188,23940,24188,24076,24188,23840,23788,24368,24188,24356,24188,24336,24188,24436,24188,24380,24188,24378,24188,24404,24188,24338,24188,24414,24188,24360,24188,24482,24188,24422,24188,24342,24188,24358,24188,24420,24188,24442,24188,24430,24188,24416,24188,24334,24188,24472,24188,24386,24188,24444,24188,24418,24188,24448,24188,24452,24188,24406,24188,24362,24188,24478,24188,24468,24188,24466,24188,24366,24188,24426,24188,24432,24188,24344,24188,24392,24188,24462,24188,24428,24188,24446,24188,24450,24188,24424,24188,24490,24188,24352,24188,24384,24188,24470,24188,24434,24188,24346,24188,24488,24188,24376,24188,24400,24188,24454,24188,24350,24188,24388,24188,24374,24188,24364,24188,24464,24188,24484,24188,24354,24188,24370,24188,24412,24188,24460,24188,24474,24188,24410,24188,24440,24188,24402,24188,24396,24188,24382,24188,24438,24188,24398,24188,24458,24188,24476,24188,24390,24188,24492,24188,24340,24188,24456,24188,24348,24188,24486,24188,24394,24188,24372,24188,24408,24188,24480,24188,23860,23788,23850,23788,23862,23788,23852,23788,23864,23788,23846,23788,23848,23788,23854,23788,23866,23788,23868,23788,23880,23788,23906,23788,23882,23788,23874,23788,23870,23788,23900,23788,23904,23788,23912,23788,23922,23788,23918,23788,23920,23788,23924,23788,23902,23788,23886,23788,23884,23788,23872,23788,23888,23788,23896,23788,23898,23788,23916,23788,23876,23788,23914,23788,23910,23788,23908,23788,23894,23788,23892,23788,23890,23788,23878,23788,23858,23788,23856,23788,23826,23788,26542,23820,23842,23820,32260,32254,32268,32254,32262,32254,32264,32254,32272,32254,32266,32254,23838,23820,23844,23820,23832,23788,23830,23788,23828,23788,25742,25740,25770,25740,25778,25740,25786,25740,25794,25740,25754,25740,25762,25740,25746,25740,25798,25740,25782,25740,25748,25740,50316,50396,25756,25740,25758,25740,25764,25740,25766,25740,-655384,50396,25780,25740,-655392,50396,25772,25740,25774,25740,-655400,50396,25796,25740,-655408,50396,25788,25740,25790,25740,-655368,50396,-655376,50396,25744,25740,-655358,50396,25750,25740,26818,25740,-655412,50396,-655396,50396,-655360,50396,50394,50396,-655504,50396,-655512,50396,-655520,50396,-655528,50396,-655488,50396,-655496,50396,-655478,50396,-655532,50396,-655516,50396,-655480,50396,50348,50396,-655250,50396,-655258,50396,-655266,50396,-655274,50396,-655234,50396,-655242,50396,-655224,50396,-655278,50396,-655262,50396,-655226,50396,50342,-655414,50376,-655160,50406,-655294]]}],"project-settings":[{"id":-1,"assetBundleId":-2,"data":[[["UnityEngine.EventSystems.EventSystem",-1000],["UnityEngine.UI.ToggleGroup",10],["TMPro.TextContainer",-110],["TMPro.TextMeshProUGUI",-100],["TMPro.TextMeshPro",-105]],[[0,"Default",0]],[[0,"Default"],[1,"TransparentFX"],[2,"Ignore Raycast"],[4,"Water"],[5,"UI"],[6,"Trap"],[7,"Destroy"],[8,"SliceParent"]],[0.0199999995529652,0.333333343267441,1,0.0299999993294477],[0,-32,0,6,2,0,1,[[0,0,0],[0,0,1],[0,0,2],[0,0,4],[0,0,5],[0,0,6],[0,0,7],[0,0,8],[0,1,0],[0,1,1],[0,1,2],[0,1,4],[0,1,5],[0,1,6],[0,1,7],[0,1,8],[0,2,0],[0,2,1],[0,2,2],[0,2,4],[0,2,5],[0,2,6],[0,2,7],[0,2,8],[0,4,0],[0,4,1],[0,4,2],[0,4,4],[0,4,5],[0,4,6],[0,4,7],[0,4,8],[0,5,0],[0,5,1],[0,5,2],[0,5,4],[0,5,5],[0,5,6],[0,5,7],[0,5,8],[0,6,0],[0,6,1],[0,6,2],[0,6,4],[0,6,5],[0,6,6],[0,6,7],[0,6,8],[0,7,0],[0,7,1],[0,7,2],[0,7,4],[0,7,5],[0,7,6],[0,7,7],[0,7,8],[0,8,0],[0,8,1],[0,8,2],[0,8,4],[0,8,5],[0,8,6],[0,8,7],[1,8,8]]],[null,null,0,-9.8100004196167,3,8,1,0.200000002980232,8,100,360,0.200000002980232,0.75,0.5,0.00999999977648258,2,0.00999999977648258,1,1,1,1,1,0,[[0,0,0],[0,0,1],[0,0,2],[0,0,4],[0,0,5],[0,0,6],[0,0,7],[0,0,8],[0,1,0],[0,1,1],[0,1,2],[0,1,4],[0,1,5],[0,1,6],[0,1,7],[0,1,8],[0,2,0],[0,2,1],[0,2,2],[0,2,4],[0,2,5],[0,2,6],[0,2,7],[0,2,8],[0,4,0],[0,4,1],[0,4,2],[0,4,4],[0,4,5],[0,4,6],[0,4,7],[0,4,8],[0,5,0],[0,5,1],[0,5,2],[0,5,4],[0,5,5],[0,5,6],[0,5,7],[0,5,8],[0,6,0],[0,6,1],[0,6,2],[0,6,4],[0,6,5],[0,6,6],[0,6,7],[0,6,8],[0,7,0],[0,7,1],[0,7,2],[0,7,4],[0,7,5],[0,7,6],[0,7,7],[0,7,8],[0,8,0],[0,8,1],[0,8,2],[0,8,4],[0,8,5],[0,8,6],[0,8,7],[0,8,8]]],[[[[],["Very Low","Low","Medium","High","Very High","Ultra"],0,0,0,0.300000011920929,1,15,0,1,0,0,0,0,0,1,2,4,0,0,0.333333343267441,0.0666666701436043,0.200000002980232,0.466666668653488,0,0,16,2,0,3,512,0,1,2,512,1,1024,0],[[],["Very Low","Low","Medium","High","Very High","Ultra"],0,0,0,0.400000005960464,1,20,0,1,0,0,0,0,0,0,2,16,0,0,0.333333343267441,0.0666666701436043,0.200000002980232,0.466666668653488,0,0,16,2,0,3,512,0,1,2,512,1,1024,1],[[],["Very Low","Low","Medium","High","Very High","Ultra"],1,1,0,0.699999988079071,1,20,0,1,0,0,0,0,0,0,2,64,1,0,0.333333343267441,0.0666666701436043,0.200000002980232,0.466666668653488,0,1,16,2,0,3,512,0,1,2,512,1,1024,2],[[],["Very Low","Low","Medium","High","Very High","Ultra"],2,1,0,1,2,40,1,1,1,0,1,0,0,0,2,256,2,1,0.333333343267441,0.0666666701436043,0.200000002980232,0.466666668653488,0,1,16,2,1,3,512,0,1,2,512,1,1024,3],[[],["Very Low","Low","Medium","High","Very High","Ultra"],2,2,2,1.5,2,70,1,1,2,1,1,0,0,0,2,1024,3,1,0.333333343267441,0.0666666701436043,0.200000002980232,0.466666668653488,0,1,16,2,1,3,512,0,1,2,512,1,1024,4],[[],["Very Low","Low","Medium","High","Very High","Ultra"],2,2,2,2,4,150,1,1,2,1,1,0,0,0,2,4096,4,1,0.333333343267441,0.0666666701436043,0.200000002980232,0.466666668653488,0,1,16,2,1,3,512,0,1,2,512,1,1024,5]],["Very Low","Low","Medium","High","Very High","Ultra"],2,2,2,2,4,150,1,1,2,1,1,0,0,0,2,4096,4,1,0.333333343267441,0.0666666701436043,0.200000002980232,0.466666668653488,0,1,16,2,1,3,512,0,1,2,512,1,1024,5],0,0,0,2,0,["Untagged","Respawn","Finish","EditorOnly","MainCamera","Player","GameController"]]}]}